gammarers/aws_frontend_web_app_deploy_stack/__init__.py
gammarers/aws_frontend_web_app_deploy_stack/py.typed
gammarers/aws_frontend_web_app_deploy_stack/_jsii/__init__.py
gammarers/aws_frontend_web_app_deploy_stack/_jsii/aws-frontend-web-app-deploy-stack@2.1.14.jsii.tgz
gammarers_aws_frontend_web_app_deploy_stack-2.1.14.dist-info/LICENSE
gammarers_aws_frontend_web_app_deploy_stack-2.1.14.dist-info/METADATA
gammarers_aws_frontend_web_app_deploy_stack-2.1.14.dist-info/WHEEL
gammarers_aws_frontend_web_app_deploy_stack-2.1.14.dist-info/top_level.txt
gammarers_aws_frontend_web_app_deploy_stack-2.1.14.dist-info/RECORD
